aiokyasher/__init__.py
aiokyasher/main.py
aiokyasher-0.0.7.dist-info/LICENSE
aiokyasher-0.0.7.dist-info/METADATA
aiokyasher-0.0.7.dist-info/WHEEL
aiokyasher-0.0.7.dist-info/top_level.txt
aiokyasher-0.0.7.dist-info/RECORD
